jupyter_server_favicon/__init__.py
jupyter_server_favicon/handlers.py
jupyter_server_favicon/static/custom/favicons/favicon-busy-1.ico
jupyter_server_favicon/static/custom/favicons/favicon.ico
jupyter_server_favicon-0.0.2.data/data/etc/jupyter/jupyter_server_config.d/jupyter_server_favicon.json
jupyter_server_favicon-0.0.2.dist-info/METADATA
jupyter_server_favicon-0.0.2.dist-info/WHEEL
jupyter_server_favicon-0.0.2.dist-info/entry_points.txt
jupyter_server_favicon-0.0.2.dist-info/licenses/LICENSE
jupyter_server_favicon-0.0.2.dist-info/RECORD
